qcodespp/__init__.py
qcodespp/actions.py
qcodespp/cli.py
qcodespp/loops.py
qcodespp/measure.py
qcodespp/parameters.py
qcodespp/station.py
qcodespp/version.py
qcodespp/data/__init__.py
qcodespp/data/data_array.py
qcodespp/data/data_set.py
qcodespp/data/format.py
qcodespp/data/gnuplot_format.py
qcodespp/data/hdf5_format.py
qcodespp/data/hdf5_format_hickle.py
qcodespp/data/io.py
qcodespp/data/location.py
qcodespp/instrument_drivers/__init__.py
qcodespp/instrument_drivers/instrument_mocks.py
qcodespp/instrument_drivers/multiplexer_instrument.py
qcodespp/instrument_drivers/Hioki/Hioki_DM7275.py
qcodespp/instrument_drivers/Hioki/__init__.py
qcodespp/instrument_drivers/Keysight/Keysight_34450A.py
qcodespp/instrument_drivers/Keysight/__init__.py
qcodespp/instrument_drivers/Keysight/private/Keysight_344xxA.py
qcodespp/instrument_drivers/Keysight/private/__init__.py
qcodespp/instrument_drivers/Lakeshore/Model_340.py
qcodespp/instrument_drivers/Lakeshore/__init__.py
qcodespp/instrument_drivers/QDevil/159fit_params_high_latest.json
qcodespp/instrument_drivers/QDevil/159fit_params_low_latest.json
qcodespp/instrument_drivers/QDevil/71fit_params_high_latest.json
qcodespp/instrument_drivers/QDevil/71fit_params_low_latest.json
qcodespp/instrument_drivers/QDevil/QDAC2.py
qcodespp/instrument_drivers/QDevil/QDAC2_Array.py
qcodespp/instrument_drivers/QDevil/QSwitch.py
qcodespp/instrument_drivers/QDevil/__init__.py
qcodespp/instrument_drivers/ZI/ZIHF2LI.py
qcodespp/instrument_drivers/ZI/ZIMFLI.py
qcodespp/instrument_drivers/ZI/ZIMFLI_sync.py
qcodespp/instrument_drivers/ZI/ZI_helpers.py
qcodespp/instrument_drivers/ZI/__init__.py
qcodespp/instrument_drivers/attocube/AMC100.py
qcodespp/instrument_drivers/attocube/__init__.py
qcodespp/instrument_drivers/cryogenic/CryogenicSMS120C.py
qcodespp/instrument_drivers/cryogenic/__init__.py
qcodespp/instrument_drivers/national_instruments/PXI_4461.py
qcodespp/instrument_drivers/national_instruments/PXI_4462.py
qcodespp-0.1.15.dist-info/entry_points.txt
qcodespp-0.1.15.dist-info/licenses/LICENSE
qcodespp-0.1.15.dist-info/WHEEL
qcodespp-0.1.15.dist-info/METADATA
qcodespp-0.1.15.dist-info/RECORD
