Metadata-Version: 2.4
Name: qcodespp
Version: 0.1.15
Summary: Package providing additional functions for QCoDeS
Maintainer-email: Damon Carrad <djcarrad@gmail.com>
Requires-Python: >=3.10
Classifier: Development Status :: 3 - Alpha
Classifier: Intended Audience :: Science/Research
Classifier: License :: OSI Approved :: MIT License
Classifier: Programming Language :: Python :: 3 :: Only
Classifier: Programming Language :: Python :: 3.10
Classifier: Programming Language :: Python :: 3.11
Classifier: Programming Language :: Python :: 3.12
Classifier: Programming Language :: Python :: 3.13
Classifier: Topic :: Scientific/Engineering
License-File: LICENSE
Requires-Dist: qcodes>=0.53
Requires-Dist: numpy>=2.2.0
Requires-Dist: pyqtgraph
Requires-Dist: matplotlib
Requires-Dist: PyQt5
Requires-Dist: ipykernel
Requires-Dist: jupyter
Requires-Dist: pyvisa
Requires-Dist: h5py>=2.6
Requires-Dist: websockets>=3.2
Requires-Dist: jsonschema
Requires-Dist: pyzmq
Requires-Dist: wrapt
Requires-Dist: pyserial
Requires-Dist: pandas
Requires-Dist: tqdm
Requires-Dist: scipy
Requires-Dist: lmfit
Project-URL: Homepage, https://github.com/qcodespp/qcodespp
